unit_propagation.py
unit_propagation-0.1.dist-info/WHEEL
unit_propagation-0.1.dist-info/METADATA
unit_propagation-0.1.dist-info/RECORD
