Metadata-Version: 2.1
Name: unit_propagation
Version: 0.1
Summary: physical quantities (numbers with units)
Keywords: quantities,physical quantity,units,SI scale factors,engineering notation,mks,cgs
Author: Ken Kundert
Author-email: quantiphy@nurdletech.com
Requires-Python: >=3.6
Classifier: Intended Audience :: Developers
Classifier: Intended Audience :: Science/Research
Classifier: License :: OSI Approved :: MIT License
Classifier: Natural Language :: English
Classifier: Operating System :: POSIX :: Linux
Classifier: Programming Language :: Python :: 3
Classifier: Topic :: Utilities
Classifier: Topic :: Scientific/Engineering
Requires-Dist: quantiphy
